PyLetterB/__init__.py
PyLetterB/getpage.py
PyLetterB/users.py
PyLetterB-0.0.1.dist-info/LICENSE.txt
PyLetterB-0.0.1.dist-info/METADATA
PyLetterB-0.0.1.dist-info/WHEEL
PyLetterB-0.0.1.dist-info/top_level.txt
PyLetterB-0.0.1.dist-info/RECORD
