Metadata-Version: 2.1
Name: PyLetterB
Version: 0.0.1
Summary: An unoffical letterboxd API for user likes
Home-page: https://github.com/Michael-Andersen/PyLB
Author: Michael Andersen
Author-email: mjpandersen@gmail.com
License: UNKNOWN
Platform: UNKNOWN
Classifier: Programming Language :: Python :: 3
Classifier: License :: OSI Approved :: MIT License
Classifier: Operating System :: OS Independent
Requires-Python: >=3.6
Requires-Dist: beautifulsoup4
